cli/__init__.py
cli/main.py
cli/commands/__init__.py
cli/commands/analyze.py
cli/commands/generate.py
cli/commands/train.py
cli/ui/__init__.py
cli/ui/console.py
cli/ui/progress.py
cli/ui/tables.py
core/__init__.py
core/models.py
core/analyzers/__init__.py
core/analyzers/stats.py
core/connectors/__init__.py
core/connectors/base.py
core/connectors/jsonl.py
core/connectors/langsmith.py
core/converters/__init__.py
core/converters/openai.py
core/filters/__init__.py
core/filters/quality.py
distillery_ai-0.1.0.dist-info/licenses/LICENSE
utils/__init__.py
utils/cost_calculator.py
distillery_ai-0.1.0.dist-info/METADATA
distillery_ai-0.1.0.dist-info/WHEEL
distillery_ai-0.1.0.dist-info/entry_points.txt
distillery_ai-0.1.0.dist-info/top_level.txt
distillery_ai-0.1.0.dist-info/RECORD
