Metadata-Version: 2.4
Name: distillery-ai
Version: 0.1.0
Summary: Convert RAG logs into fine-tuning datasets
Home-page: https://github.com/yourusername/distillery
Author: Distillery
Author-email: Distillery Team <hello@distillery.ai>
License: MIT License
Project-URL: Homepage, https://github.com/josharsh/distillery
Project-URL: Documentation, https://docs.distillery.ai
Project-URL: Repository, https://github.com/josharsh/distillery
Project-URL: Bug Tracker, https://github.com/josharsh/distillery/issues
Keywords: fine-tuning,rag,llm,openai,training-data,machine-learning
Classifier: Development Status :: 3 - Alpha
Classifier: Intended Audience :: Developers
Classifier: Topic :: Software Development :: Libraries :: Python Modules
Classifier: License :: OSI Approved :: MIT License
Classifier: Programming Language :: Python :: 3
Classifier: Programming Language :: Python :: 3.9
Classifier: Programming Language :: Python :: 3.10
Classifier: Programming Language :: Python :: 3.11
Classifier: Programming Language :: Python :: 3.12
Requires-Python: >=3.9
License-File: LICENSE
Requires-Dist: click>=8.0.0
Requires-Dist: rich>=13.0.0
Requires-Dist: openai>=1.0.0
Provides-Extra: langsmith
Requires-Dist: langsmith>=0.1.0; extra == "langsmith"
Provides-Extra: dev
Requires-Dist: pytest>=7.0.0; extra == "dev"
Requires-Dist: black>=23.0.0; extra == "dev"
Requires-Dist: mypy>=1.0.0; extra == "dev"
Requires-Dist: build>=0.10.0; extra == "dev"
Requires-Dist: twine>=4.0.0; extra == "dev"
Dynamic: author
Dynamic: home-page
Dynamic: license-file
Dynamic: requires-python
